sonicmesh/__init__.py
sonicmesh/acoustic_config.py
sonicmesh/decode_wav.py
sonicmesh/decoder.py
sonicmesh/encoder.py
sonicmesh/receive.py
sonicmesh/transmit.py
sonicmesh-0.1.7.dist-info/licenses/LICENSE
sonicmesh-0.1.7.dist-info/METADATA
sonicmesh-0.1.7.dist-info/WHEEL
sonicmesh-0.1.7.dist-info/top_level.txt
sonicmesh-0.1.7.dist-info/RECORD
