Metadata-Version: 2.4
Name: sonicmesh
Version: 0.1.7
Summary: Acoustic communication library for audio-based data transfer
Author: Sukhdev Thukral
License: MIT License
Project-URL: Homepage, https://github.com/SukhdevThukral/SonicMesh
Requires-Python: >=3.8
License-File: LICENSE
Requires-Dist: numpy>=1.24
Requires-Dist: sounddevice>=0.4
Requires-Dist: soundfile>=0.12
Requires-Dist: scipy>=1.11
Dynamic: license-file
